{
  "ElapsedTime": {
    "Counts": {
      "Adaptation": 0,
      "CoarseSolve": 21,
      "Construction": 1,
      "DiskIO": 5,
      "Div.-FreeProjection": 0,
      "EigenvalueSolve": 0,
      "Estimation": 2,
      "Initialization": 2,
      "LinearSolve": 2,
      "MeshPreprocessing": 1,
      "OperatorConstruction": 1,
      "PROMConstruction": 0,
      "PROMSolve": 0,
      "Postprocessing": 6,
      "Preconditioner": 21,
      "Rebalancing": 0,
      "Setup": 1,
      "Solve": 2,
      "TimeStepping": 0,
      "Total": 1,
      "WavePorts": 0
    },
    "Durations": {
      "Adaptation": 0.0,
      "CoarseSolve": 0.009254473000000001,
      "Construction": 2.23458302,
      "DiskIO": 7.961810870000001,
      "Div.-FreeProjection": 0.0,
      "EigenvalueSolve": 0.0,
      "Estimation": 0.046285372,
      "Initialization": 0.297368318,
      "LinearSolve": 0.153914338,
      "MeshPreprocessing": 0.423546525,
      "OperatorConstruction": 4.181939164000001,
      "PROMConstruction": 0.0,
      "PROMSolve": 0.0,
      "Postprocessing": 0.14659759399999994,
      "Preconditioner": 3.690275587,
      "Rebalancing": 0.0,
      "Setup": 2.113377935,
      "Solve": 2.219208094,
      "TimeStepping": 0.0,
      "Total": 23.489862153,
      "WavePorts": 0.0
    }
  },
  "GitTag": "v0.14.0",
  "LinearSolver": {
    "TotalIts": 17,
    "TotalSolves": 2
  },
  "Problem": {
    "DegreesOfFreedom": 66328,
    "MPISize": 1,
    "MeshElements": 14362,
    "MultigridDegreesOfFreedom": [
      2536,
      19857,
      66328
    ]
  }
}
